{
    "objects": [
        {
            "id": "role-geophysicist",
            "name": "Geophysicist",
            "typeRef": "0006897b-07c2-4824-683f-2c10146e1a4a",
            "typeName": "Role",
            "description": "Responsible for seismic data collection and preliminary analysis."
        },
        {
            "id": "task-seismic-data-collection",
            "name": "Seismic Data Collection",
            "typeRef": "a7661dac-4deb-4668-81f3-0248d46f1c7e",
            "typeName": "Task",
            "description": "Collecting seismic data using various techniques and equipment."
        },
        {
            "id": "info-seismic-data",
            "name": "Seismic Data",
            "typeRef": "05ea3e5c-e9a1-43f5-31a4-042acc4dbdbb",
            "typeName": "Information",
            "description": "Raw data collected from seismic surveys."
        }
    ],
    "relships": [
        {
            "id": "rel-geophysicist-seismic-data-collection",
            "name": "performs",
            "typeRef": "f46856b9-3041-41bd-239b-3db729390a73",
            "fromobjectRef": "role-geophysicist",
            "toobjectRef": "task-seismic-data-collection",
            "description": "Geophysicist performs Seismic Data Collection"
        },
        {
            "id": "rel-seismic-data-collection-seismic-data",
            "name": "hasOutput",
            "typeRef": "ef25d26e-2324-4633-2d9a-1e9f2ca82ea4",
            "fromobjectRef": "task-seismic-data-collection",
            "toobjectRef": "info-seismic-data",
            "description": "Seismic Data Collection outputs Seismic Data"
        }
    ]
}